LICENSE
MANIFEST.in
README.md
env.yml
mac_env.yml
pytest.ini
release.sh
requirements.txt
setup.py
pb_multiscale_actin/__init__.py
pb_multiscale_actin/create_readdy_pbif.py
pb_multiscale_actin.egg-info/PKG-INFO
pb_multiscale_actin.egg-info/SOURCES.txt
pb_multiscale_actin.egg-info/dependency_links.txt
pb_multiscale_actin.egg-info/requires.txt
pb_multiscale_actin.egg-info/top_level.txt
pb_multiscale_actin/composites/__init__.py
pb_multiscale_actin/experiments/__init__.py
pb_multiscale_actin/processes/__init__.py
pb_multiscale_actin/processes/readdy_actin_membrane.py
pb_multiscale_actin/processes/simularium_emitter.py