Metadata-Version: 2.4
Name: pb_multiscale_actin
Version: 1.2.4
Home-page: 
Author: Blair Lyons
Author-email: blair208@gmail.com
License: Apache Software License 2.0
License-File: LICENSE
Requires-Dist: vivarium-core
Requires-Dist: process-bigraph
Requires-Dist: simularium-readdy-models
Dynamic: author
Dynamic: author-email
Dynamic: description
Dynamic: description-content-type
Dynamic: license
Dynamic: license-file
Dynamic: requires-dist
